pyqt6rc/__init__.py
pyqt6rc/convert_tools.py
pyqt6rc/script_helpers.py
pyqt6rc/scripts/__init__.py
pyqt6rc/scripts/pyqt6rc.py
pyqt6rc/scripts/pyqt6sp.py
pyqt6rc/scripts/pyside6rc.py
pyqt6rc/test/__init__.py
pyqt6rc/test/test_convert_tools.py
pyqt6rc/test/test_resources/broken_resources.qrc
pyqt6rc/test/test_resources/myPackage/__init__.py
pyqt6rc/test/test_resources/myPackage/resources/__init__.py
pyqt6rc/test/test_resources/myPackage/resources/icons/__init__.py
pyqt6rc/test/test_resources/myPackage/resources/icons/icon1.png
pyqt6rc/test/test_resources/myPackage/resources/icons/icon1_r2.png
pyqt6rc/test/test_resources/myPackage/resources/icons/icon2.png
pyqt6rc/test/test_resources/myPackage/resources/icons/icon2_r2.png
pyqt6rc/test/test_resources/myPackage/resources/image1.png
pyqt6rc/test/test_resources/myPackage/resources/image1_r2.png
pyqt6rc/test/test_resources/myPackage/resources/image2.png
pyqt6rc/test/test_resources/myPackage/resources/image2_r2.png
pyqt6rc/test/test_resources/myPackage/resources/pyqt6_resources.py
pyqt6rc/test/test_resources/myPackage/resources/pyside_resources.py
pyqt6rc/test/test_resources/myPackage/resources/resources.qrc
pyqt6rc/test/test_resources/myPackage/resources/second_resources.qrc
pyqt6rc/test/test_resources/myPackage/templates/__init__.py
pyqt6rc/test/test_resources/myPackage/templates/template1.py
pyqt6rc/test/test_resources/myPackage/templates/template1.ui
pyqt6rc/test/test_resources/myPackage/templates/template1_reference.py
pyqt6rc/test/test_resources/myPackage/templates/template1_reference_compatible.py
pyqt6rc/test/test_resources/myPackage/templates/template1_sp_reference.py
pyqt6rc/test/test_resources/myPackage/templates/template2.py
pyqt6rc/test/test_resources/myPackage/templates/template2.ui
pyqt6rc/test/test_resources/myPackage/templates/template2_reference.py
pyqt6rc/test/test_resources/myPackage/templates/template2_reference_compatible.py
pyqt6rc/test/test_resources/myPackage/templates/template2_sp_reference.py
pyqt6rc-0.7.1.dist-info/LICENSE
pyqt6rc-0.7.1.dist-info/METADATA
pyqt6rc-0.7.1.dist-info/WHEEL
pyqt6rc-0.7.1.dist-info/entry_points.txt
pyqt6rc-0.7.1.dist-info/RECORD
