Metadata-Version: 2.1
Name: pyqt6rc
Version: 0.7.1
Summary: PyQt6 UI templates resource converter
Home-page: https://github.com/domarm-comat/pyqt6rc
License: MIT
Keywords: pyqt6,converter,resources,resource-management
Author: Martin Domaracký
Author-email: domarm@comat.sk
Requires-Python: >=3.9,<3.13
Classifier: Intended Audience :: Developers
Classifier: License :: OSI Approved :: MIT License
Classifier: Natural Language :: English
Classifier: Operating System :: OS Independent
Classifier: Programming Language :: Python :: 3
Classifier: Programming Language :: Python :: 3.9
Classifier: Programming Language :: Python :: 3.10
Classifier: Programming Language :: Python :: 3.11
Classifier: Programming Language :: Python :: 3.12
Classifier: Topic :: Software Development :: Libraries
Requires-Dist: importlib-resources (>=5.12.0,<6.0.0)
Requires-Dist: pyqt6 (>=6.5.0,<7.0.0)
Requires-Dist: pyside6 (>=6.8.0.2,<7.0.0.0)
Project-URL: Repository, https://github.com/domarm-comat/pyqt6rc
